doc2markdown/__init__.py
doc2markdown/converter.py
doc2markdown-0.1.2.dist-info/LICENSE
doc2markdown-0.1.2.dist-info/METADATA
doc2markdown-0.1.2.dist-info/WHEEL
doc2markdown-0.1.2.dist-info/entry_points.txt
doc2markdown-0.1.2.dist-info/top_level.txt
doc2markdown-0.1.2.dist-info/RECORD
