Metadata-Version: 2.1
Name: doc2markdown
Version: 0.1.2
Summary: A tool to convert various document formats to Markdown
Home-page: https://github.com/adam404/doc2markdown
Author: Your Name
Author-email: me@adamscott.info
Classifier: Programming Language :: Python :: 3
Classifier: License :: OSI Approved :: MIT License
Classifier: Operating System :: OS Independent
Requires-Python: >=3.6
License-File: LICENSE
Requires-Dist: PyPDF2
Requires-Dist: python-pptx
Requires-Dist: python-docx
Requires-Dist: pycryptodome
